task_grouping.py
task_grouping-0.1a5.dist-info/LICENSE
task_grouping-0.1a5.dist-info/METADATA
task_grouping-0.1a5.dist-info/WHEEL
task_grouping-0.1a5.dist-info/top_level.txt
task_grouping-0.1a5.dist-info/RECORD
