Metadata-Version: 2.1
Name: task-grouping
Version: 0.1a5
Summary: Task Grouping
Home-page: https://github.com/DataBooster/PyWebApi
Author: Abel Cheng
Author-email: abelcys@gmail.com
License: MIT
Keywords: grouping,tasks,parallel,serial,pipeline,arguments,container,loader,JSON,tree
Platform: any
Requires-Python: >=3.5
